{
  "summary": {
    "debtServiceRatio": 0.2413,
    "totalMonthlyPaymentKrw": 1109827,
    "warningsCount": 0
  },
  "warnings": [],
  "summaries": [
    {
      "liabilityId": "demo-loan-1",
      "name": "주택담보대출",
      "type": "amortizing",
      "principalKrw": 180000000,
      "aprPct": 4.2,
      "remainingMonths": 240,
      "monthlyPaymentKrw": 1109827,
      "monthlyInterestKrw": 630000,
      "totalInterestRemainingKrw": 86358558,
      "payoffMonthIndex": 241
    }
  ],
  "whatIf": {
    "termExtensions": [],
    "termReductions": [
      {
        "liabilityId": "demo-loan-1",
        "newTermMonths": 12,
        "newMonthlyPaymentKrw": 15343436,
        "notes": [
          "Assumes same principal and APR; only term changed."
        ]
      },
      {
        "liabilityId": "demo-loan-1",
        "newTermMonths": 24,
        "newMonthlyPaymentKrw": 7832519,
        "notes": [
          "Assumes same principal and APR; only term changed."
        ]
      },
      {
        "liabilityId": "demo-loan-1",
        "newTermMonths": 36,
        "newMonthlyPaymentKrw": 5330347,
        "notes": [
          "Assumes same principal and APR; only term changed."
        ]
      },
      {
        "liabilityId": "demo-loan-1",
        "newTermMonths": 60,
        "newMonthlyPaymentKrw": 3331245,
        "notes": [
          "Assumes same principal and APR; only term changed."
        ]
      },
      {
        "liabilityId": "demo-loan-1",
        "newTermMonths": 120,
        "newMonthlyPaymentKrw": 1839571,
        "notes": [
          "Assumes same principal and APR; only term changed."
        ]
      }
    ],
    "extraPayments": []
  }
}
